{
  "project_info": {
    "project_number": "421313407099",
    "project_id": "hireacar-5d299",
    "storage_bucket": "hireacar-5d299.appspot.com"
  },
  "client": [
    {
      "client_info": {
        "mobilesdk_app_id": "1:421313407099:android:33a24e27f367c3425e9ade",
        "android_client_info": {
          "package_name": "com.hireacar"
        }
      },
      "oauth_client": [
        {
          "client_id": "421313407099-9b9cep98e7n6qatuka3jbhl6ia8d93kf.apps.googleusercontent.com",
          "client_type": 1,
          "android_info": {
            "package_name": "com.hireacar",
            "certificate_hash": "5e8f16062ea3cd2c4a0d547876baa6f38cabf625"
          }
        },
        {
          "client_id": "421313407099-ehfuivfr1dcibch496vpm0dss9ssks0c.apps.googleusercontent.com",
          "client_type": 3
        }
      ],
      "api_key": [
        {
          "current_key": "AIzaSyCT0Ie-C-MOWrJ_r5f6Q1ZpPwkSOeuKANU"
        }
      ],
      "services": {
        "appinvite_service": {
          "other_platform_oauth_client": [
            {
              "client_id": "421313407099-ehfuivfr1dcibch496vpm0dss9ssks0c.apps.googleusercontent.com",
              "client_type": 3
            },
            {
              "client_id": "421313407099-giu29dfu1evm084knc25tfpg5359efet.apps.googleusercontent.com",
              "client_type": 2,
              "ios_info": {
                "bundle_id": "com.hireacar"
              }
            }
          ]
        }
      }
    }
  ],
  "configuration_version": "1"
}